rail_pz_service/__init__.py
rail_pz_service/_version.py
rail_pz_service/config.py
rail_pz_service/client/__init__.py
rail_pz_service/client/algorithm.py
rail_pz_service/client/catalog_tag.py
rail_pz_service/client/client.py
rail_pz_service/client/clientconfig.py
rail_pz_service/client/dataset.py
rail_pz_service/client/estimator.py
rail_pz_service/client/load.py
rail_pz_service/client/model.py
rail_pz_service/client/py.typed
rail_pz_service/client/request.py
rail_pz_service/client/wrappers.py
rail_pz_service/client/cli/__init__.py
rail_pz_service/client/cli/algorithm.py
rail_pz_service/client/cli/catalog_tag.py
rail_pz_service/client/cli/client_options.py
rail_pz_service/client/cli/dataset.py
rail_pz_service/client/cli/estimator.py
rail_pz_service/client/cli/load.py
rail_pz_service/client/cli/main.py
rail_pz_service/client/cli/model.py
rail_pz_service/client/cli/py.typed
rail_pz_service/client/cli/request.py
rail_pz_service/client/cli/wrappers.py
rail_pz_service/common/__init__.py
rail_pz_service/common/common_options.py
rail_pz_service/common/errors.py
rail_pz_service/common/py.typed
rail_pz_service/common/test_files.py
rail_pz_service/db/__init__.py
rail_pz_service/db/algorithm.py
rail_pz_service/db/base.py
rail_pz_service/db/cache.py
rail_pz_service/db/catalog_tag.py
rail_pz_service/db/dataset.py
rail_pz_service/db/estimator.py
rail_pz_service/db/model.py
rail_pz_service/db/py.typed
rail_pz_service/db/request.py
rail_pz_service/db/row.py
rail_pz_service/db/cli/__init__.py
rail_pz_service/db/cli/admin.py
rail_pz_service/db/cli/admin_options.py
rail_pz_service/db/cli/algorithm.py
rail_pz_service/db/cli/catalog_tag.py
rail_pz_service/db/cli/dataset.py
rail_pz_service/db/cli/estimator.py
rail_pz_service/db/cli/load.py
rail_pz_service/db/cli/model.py
rail_pz_service/db/cli/py.typed
rail_pz_service/db/cli/request.py
rail_pz_service/db/cli/wrappers.py
rail_pz_service/models/__init__.py
rail_pz_service/models/algorithm.py
rail_pz_service/models/catalog_tag.py
pz_rail_service-0.0.3.dist-info/LICENSE
pz_rail_service-0.0.3.dist-info/METADATA
pz_rail_service-0.0.3.dist-info/WHEEL
pz_rail_service-0.0.3.dist-info/entry_points.txt
pz_rail_service-0.0.3.dist-info/top_level.txt
pz_rail_service-0.0.3.dist-info/RECORD
