Metadata-Version: 2.2
Name: pz-rail-service
Version: 0.0.3
Summary: RAIL service to generate photometric redshifts, umbrellla
License: MIT License
Project-URL: Source, https://github.com/LSSTDESC/rail_pz_service
Classifier: Development Status :: 4 - Beta
Classifier: License :: OSI Approved :: MIT License
Classifier: Programming Language :: Python
Classifier: Programming Language :: Python :: 3
Classifier: Programming Language :: Python :: 3.11
Classifier: Intended Audience :: Developers
Classifier: Natural Language :: English
Classifier: Operating System :: POSIX
Classifier: Typing :: Typed
Requires-Python: <3.12,>=3.11
License-File: LICENSE
Requires-Dist: click
Requires-Dist: dotenv
Requires-Dist: httpx>=0.27.2
Requires-Dist: pre-commit>=4.0.1
Requires-Dist: setuptools
Requires-Dist: pydantic==2.10.*
Requires-Dist: pydantic-settings==2.7.*
Requires-Dist: tabulate==0.9.*
Provides-Extra: server
Requires-Dist: alembic==1.14.*; extra == "server"
Requires-Dist: anyio==4.7.*; extra == "server"
Requires-Dist: asyncio; extra == "server"
Requires-Dist: ceci; extra == "server"
Requires-Dist: click; extra == "server"
Requires-Dist: dotenv; extra == "server"
Requires-Dist: fastapi==0.115.*; extra == "server"
Requires-Dist: httpx>=0.27.2; extra == "server"
Requires-Dist: jinja2; extra == "server"
Requires-Dist: numpy==2.1.*; extra == "server"
Requires-Dist: pydantic==2.10.*; extra == "server"
Requires-Dist: pydantic-settings==2.7.*; extra == "server"
Requires-Dist: psycopg2-binary; extra == "server"
Requires-Dist: qp-prob[full]; extra == "server"
Requires-Dist: pz-rail; extra == "server"
Requires-Dist: safir[db]==7.0.*; extra == "server"
Requires-Dist: sqlalchemy[asyncio]==2.0.*; extra == "server"
Requires-Dist: structlog==24.4.*; extra == "server"
Requires-Dist: tables_io[full]; extra == "server"
Requires-Dist: tabulate==0.9.*; extra == "server"
Requires-Dist: uvicorn; extra == "server"
Provides-Extra: dev
Requires-Dist: pz-rail-service[server]; extra == "dev"
Requires-Dist: aiosqlite>=0.20.0; extra == "dev"
Requires-Dist: alembic==1.14.*; extra == "dev"
Requires-Dist: asyncio; extra == "dev"
Requires-Dist: asgi-lifespan>=2.1.0; extra == "dev"
Requires-Dist: coverage[toml]>=7.6.7; extra == "dev"
Requires-Dist: greenlet>=3.1.1; extra == "dev"
Requires-Dist: httpx>=0.27.2; extra == "dev"
Requires-Dist: mypy>=1.13.0; extra == "dev"
Requires-Dist: pre-commit>=4.0.1; extra == "dev"
Requires-Dist: pydantic==2.10.*; extra == "dev"
Requires-Dist: psycopg2-binary; extra == "dev"
Requires-Dist: pytest>=8.3.3; extra == "dev"
Requires-Dist: pytest-asyncio>=0.24.0; extra == "dev"
Requires-Dist: pytest-cov>=6.0.0; extra == "dev"
Requires-Dist: pytest-timeout>=2.3.1; extra == "dev"
Requires-Dist: qp-prob[full]; extra == "dev"
Requires-Dist: ruff>=0.8.0; extra == "dev"
Requires-Dist: safir[db]==7.0.*; extra == "dev"
Requires-Dist: sqlalchemy[mypy]>=2.0.36; extra == "dev"
Requires-Dist: sqlalchemy[asyncio]==2.0.*; extra == "dev"
Requires-Dist: structlog==24.4.*; extra == "dev"
Requires-Dist: types-pyyaml>=6.0.12.20240917; extra == "dev"
Requires-Dist: types-tabulate>=0.9.0.20240106; extra == "dev"
Provides-Extra: docs
Requires-Dist: nbsphinx; extra == "docs"
Requires-Dist: sphinx; extra == "docs"
Requires-Dist: sphinx-autodoc-typehints; extra == "docs"
Requires-Dist: sphinx_rtd_theme; extra == "docs"
Requires-Dist: sphinx-autoapi; extra == "docs"
Requires-Dist: sphinx-tabs; extra == "docs"
Requires-Dist: sphinx-click; extra == "docs"
Provides-Extra: all
Requires-Dist: pz-rail-service; extra == "all"
Requires-Dist: pz-rail-service[server]; extra == "all"
Requires-Dist: pz-rail-service[dev]; extra == "all"
Requires-Dist: pz-rail-service[docs]; extra == "all"
